[
    {
      "key": "servdep01",
      "type": "img_plus_input",
      "label": "Complete com as medidas em metros nos itens a seguir:",
      "placeholder": "",
      "description": "",
      "default_value": "Saliva de pirulito",
      "additonal_type": null,
      "image": "servcozinha1",
      "radio": null,
      "input": {
        "dependency": null,
        "fields": [
          {
            "key": "A",
            "label": "A - ",
          },
          {
            "key": "B",
            "label": "B - ",
          },
          {
            "key": "B",
            "label": "B - ",
          },
          {
            "key": "C",
            "label": "C - ",
          },
          {
            "key": "D",
            "label": "D - ",
          },
          {
            "key": "E",
            "label": "E - ",
          },
          {
            "key": "F",
            "label": "F - ",
          },
          {
            "key": "G",
            "label": "G - ",
          },
          {
            "key": "H",
            "label": "H - ",
          },
          {
            "key": "I",
            "label": "I - ",
          },
          {
            "key": "J",
            "label": "J - ",
          },
          {
            "key": "K",
            "label": "K - ",
          },
          {
            "key": "L",
            "label": "L - ",
          },
          {
            "key": "M",
            "label": "M - ",
          },
          {
            "key": "N",
            "label": "N - ",
          },
          {
            "key": "Area",
            "label": "Area - ",
          },
          {
            "key": "Perimetro",
            "label": "Perimetro - ",
          },
          {
            "key": "Pe-direito",
            "label": "Pe-direito - ",
          }
        ]
      }
    },
    {
      "key": "sercozinha02",
      "type": "img_plus_input",
      "label": "De acordo as descrições apresentadas, verifique se as esquadrias foram instaladas corretamente:",
      "placeholder": "",
      "description": "",
      "default_value": "Saliva de pirulito",
      "additonal_type": null,
      "image": "servcozinha2",
      "radio": null,
      "input": {
        "dependency": null,
        "fields": [
          {
            "key": "ef15",
            "label": "Quantidade instalada EF 15?",
          },
          {
            "key": "e21",
            "label": "Quantidade instalada EF 21?",
          },
          {
            "key": "ef11",
            "label": "Quantidade instalada EF 11?",
          },
          {
            "key": "pm04b",
            "label": "Quantidade instalada PM04B?",
          },
          {
            "key": "ep03",
            "label": "Quantidade instalada P 03?",
          },
          {
            "key": "ef10",
            "label": "Quantidade instalada EF 10?",
          },
          {
            "key": "ef16",
            "label": "Quantidade instalada EF 16?",
          },
          {
            "key": "ef20",
            "label": "Quantidade instalada EF 20?",
          },
        ]
      }
    },
    {
        "key": "sercozinha03",
        "type": "text",
        "label": "Quantas luminárias de sobrepor com 2 lâmpadas 32W foram instaladas?",
        "placeholder": "",
        "description": "",
        "default_value": "",
        "additional_type": null,
      },
    {
      "key": "sercozinha04",
      "type": "img_plus_input",
      "label": "As bancadas de granito foram instaladas?",
      "placeholder": "",
      "description": "",
      "default_value": null,
      "additonal_type": null,
      "image": "servcozinha3",
      "radio": [
        {
          "id": 0,
          "description": "Não",
        },
        {
          "id": 2,
          "description": "Sim, com as seguintes dimensões em  metros:",
        }
      ],
      "input": {
        "dependency": {
          "key": "radio",
          "value": 2
        },
        "fields": [
          {
            "key": "Comprimento",
            "label": "Comprimento da bancada 1: ",
          },
          {
            "key": "Largura da bancada 1",
            "label": "Largura: ",
          },
          {
            "key": "Comprimento",
            "label": "Comprimento da bancada 2: ",
          },
          {
            "key": "Largura da bancada 2",
            "label": "Largura: ",
          },
          {
            "key": "Comprimento",
            "label": "Comprimento da bancada 3: ",
          },
          {
            "key": "Largura da bancada 3",
            "label": "Largura: ",
          },
          {
            "key": "Comprimento",
            "label": "Comprimento da bancada 4: ",
          },
          {
            "key": "Largura da bancada 4",
            "label": "Largura: ",
          },
          {
            "key": "Comprimento",
            "label": "Comprimento da bancada 5: ",
          },
          {
            "key": "Largura da bancada 5",
            "label": "Largura: ",
          },
          {
            "key": "Comprimento",
            "label": "Comprimento da bancada 6: ",
          },
          {
            "key": "Largura da bancada 6",
            "label": "Largura: ",
          },

        ]
      }
    },
    {
      "key": "sercozinha05",
      "type": "picker",
      "label": "Qual tipo de piso foi instalado?",
      "description": "Selecionar alguma opção",
      "placeholder": "exemplo",
      "default_value": "",
      "aditional_type": null,
      "options": [
        "Bloco de concreto intertravado",
        "Cerâmico",
        "Cimento desempenado",
        "Granitina",
        "Outros"
      ],
    },
    {
      "key": "sercozinha06",
      "type": "img_plus_input",
      "label": "O teto foi pintado?",
      "placeholder": "",
      "description": "",
      "default_value": null,
      "additonal_type": null,
      "image": null,
      "radio": [
        {
          "id": 0,
          "description": "Não",
        },
        {
          "id": 2,
          "description": "Sim",
        }
      ]
    },
    {
        "key": "sercozinha07",
        "type": "img_plus_input",
        "label": "A cerâmica 20 cm x 20 cm foi aplicada na parede toda?",
        "placeholder": "",
        "description": "",
        "default_value": null,
        "additonal_type": null,
        "image": null,
        "radio": [
          {
            "id": 0,
            "description": "Não",
          },
          {
            "id": 2,
            "description": "Sim",
          }
        ],
        "input": {
          "dependency": {
            "key": "radio",
            "value": 0
          },
          "fields": [
            {
              "key": "revestimento",
              "label": "Não, em:",
            },
          ]
        }
      },
    {
      "key": "sercozinha08",
      "type": "img_plus_input",
      "label": "O revestimento foi aplicado em todo perímetro?",
      "placeholder": "",
      "description": "",
      "default_value": null,
      "additonal_type": null,
      "image": null,
      "radio": [
        {
          "id": 0,
          "description": "Não",
        },
        {
          "id": 2,
          "description": "Sim",
        }
      ],
      "input": {
        "dependency": {
          "key": "radio",
          "value": 0
        },
        "fields": [
          {
            "key": "revestimento",
            "label": "Não, em:",
          },
        ]
      }
    }
  ]
  